generic_report_generator
