Metadata-Version: 1.1
Name: generic-report-generator
Version: 0.0.4
Summary: The generic report generator
Home-page: https://github.com/davidNHK/generic-report-generator
Author: David Ng
Author-email: david.ng.dev@gmail.com
License: BSD
Download-URL: https://github.com/davidNHK/generic-report-generator/archive/0.0.4.zip
Keywords: sqlalchemy,job queue,worker
Platform: UNKNOWN
